pyus/__init__.py
pyus/_version.py
pyus/_build_utils/__init__.py
pyus/_build_utils/cuda.py
pyus/_build_utils/cython.py
pyus/_build_utils/file_utils.py
pyus/_build_utils/git.py
pyus/_build_utils/install.py
pyus/core/__init__.py
pyus/core/cython/__init__.py
pyus/core/cython/imaging/__init__.py
pyus/core/cython/imaging/das/__init__.py
pyus/core/cython/imaging/das/das_rf.cpp
pyus/core/cython/imaging/das/das_rf.cpython-35m-x86_64-linux-gnu.so
pyus/core/cython/imaging/das/das_rf.pxd
pyus/core/cython/imaging/functors/__init__.py
pyus/core/cython/imaging/functors/delays.cpp
pyus/core/cython/imaging/functors/delays.cpython-35m-x86_64-linux-gnu.so
pyus/core/cython/imaging/functors/delays.pxd
pyus/core/cython/imaging/functors/utils.cpp
pyus/core/cython/imaging/functors/utils.cpython-35m-x86_64-linux-gnu.so
pyus/core/cython/imaging/functors/utils.pxd
pyus/core/cython/imaging/functors/windows.cpp
pyus/core/cython/imaging/functors/windows.cpython-35m-x86_64-linux-gnu.so
pyus/core/cython/imaging/functors/windows.pxd
pyus/core/cython/imaging/interpolator/__init__.py
pyus/core/cython/imaging/interpolator/interpolator.cpp
pyus/core/cython/imaging/interpolator/interpolator.cpython-35m-x86_64-linux-gnu.so
pyus/core/cython/imaging/interpolator/interpolator.pxd
pyus/core/cython/imaging/interpolator/prefilter.cpp
pyus/core/cython/imaging/interpolator/prefilter.cpython-35m-x86_64-linux-gnu.so
pyus/core/cython/imaging/interpolator/prefilter.pxd
pyus/core/cython/imaging/interpolator/prefiltering.py
pyus/core/cython/signal/__init__.py
pyus/core/cython/signal/convolution.cpp
pyus/core/cython/signal/convolution.cpython-35m-x86_64-linux-gnu.so
pyus/core/cython/signal/convolution.pxd
pyus/core/cython/signal/hilbert.cpp
pyus/core/cython/signal/hilbert.cpython-35m-x86_64-linux-gnu.so
pyus/core/cython/signal/hilbert.pxd
pyus/core/cython/signal/utils.cpp
pyus/core/cython/signal/utils.cpython-35m-x86_64-linux-gnu.so
pyus/core/cython/signal/utils.pxd
pyus-0.2.2.dist-info/LICENSE.txt
pyus-0.2.2.dist-info/METADATA
pyus-0.2.2.dist-info/RECORD
pyus-0.2.2.dist-info/WHEEL
pyus-0.2.2.dist-info/top_level.txt
