Metadata-Version: 2.1
Name: pyus
Version: 0.2.2
Summary: GPU-accelerated Python package for ultrasound imaging.
Home-page: https://gitlab.com/pyus/pyus
Author: Dimitris Perdios, Florian Martinez
License: BSD-3
Download-URL: https://gitlab.com/pyus/pyus/tags
Project-URL: Bug Tracker, https://gitlab.com/pyus/pyus/issues
Project-URL: Source Code, https://gitlab.com/pyus/pyus
Keywords: ultrasound imaging gpu
Platform: Linux
Classifier: Development Status :: 4 - Beta
Classifier: Intended Audience :: Developers
Classifier: Intended Audience :: Education
Classifier: Intended Audience :: Healthcare Industry
Classifier: Intended Audience :: Science/Research
Classifier: Environment :: Console
Classifier: License :: OSI Approved :: BSD License
Classifier: Programming Language :: Python :: 3.5
Classifier: Programming Language :: Python :: 3.6
Classifier: Programming Language :: Python :: 3.7
Classifier: Programming Language :: Python :: 3.8
Classifier: Topic :: Scientific/Engineering
Classifier: Topic :: Scientific/Engineering :: Mathematics
Classifier: Topic :: Scientific/Engineering :: Medical Science Apps.
Classifier: Topic :: Scientific/Engineering :: Physics
Classifier: Operating System :: POSIX :: Linux
Requires-Python: >=3.5
Provides-Extra: doc
Provides-Extra: dev
Provides-Extra: pkg
Requires-Dist: numpy (>=1.17.3)
Requires-Dist: scipy (<1.4,>=1.3.1)
Requires-Dist: h5py (>=2.10.0)
Requires-Dist: matplotlib (>=3.0.3)
Requires-Dist: tqdm (>=4.36.1)
Requires-Dist: pyfftw (>=0.11.1)
Requires-Dist: pycuda (>=2019.1.2)
Provides-Extra: dev
Requires-Dist: Cython; extra == 'dev'
Provides-Extra: doc
Requires-Dist: Sphinx; extra == 'doc'
Provides-Extra: pkg
Requires-Dist: wheel; extra == 'pkg'
Requires-Dist: twine; extra == 'pkg'
